LICENSE
MANIFEST.in
README.md
setup.py
publishstatic/__init__.py
publishstatic.egg-info/PKG-INFO
publishstatic.egg-info/SOURCES.txt
publishstatic.egg-info/dependency_links.txt
publishstatic.egg-info/requires.txt
publishstatic.egg-info/top_level.txt
publishstatic/management/__init__.py
publishstatic/management/commands/__init__.py
publishstatic/management/commands/common.py
publishstatic/management/commands/publishstatic.py
publishstatic/management/commands/utils.py
publishstatic/management/commands/storage/__init__.py
publishstatic/management/commands/storage/local.py
publishstatic/management/commands/storage/s3.py