Metadata-Version: 1.1
Name: publishstatic
Version: 0.1.1
Summary: Django management command to upload changed static files.
Home-page: http://github.com/scuml/publishstatic
Author: Stephen Mitchell
Author-email: stephen@echodot.com
License: Copyright 2016 Stephen Mitchell
